graphrag_tagger/__init__.py
graphrag_tagger/build_graph.py
graphrag_tagger/tagger.py
graphrag_tagger/chat/__init__.py
graphrag_tagger/chat/llm.py
graphrag_tagger/chat/parser.py
graphrag_tagger/chat/prompts.py
graphrag_tagger/lda/__init__.py
graphrag_tagger/lda/kt_modelling.py
graphrag_tagger/lda/sk_modelling.py
tests/__init__.py
tests/test_build_graph.py
tests/test_integration.py
tests/test_ktrain_topic_extractor.py
tests/test_llm.py
tests/test_parser.py
tests/test_sklearn_topic_extractor.py
tests/test_tagger.py
graphrag_tagger-0.1.1.dist-info/LICENSE
graphrag_tagger-0.1.1.dist-info/METADATA
graphrag_tagger-0.1.1.dist-info/WHEEL
graphrag_tagger-0.1.1.dist-info/top_level.txt
graphrag_tagger-0.1.1.dist-info/RECORD
