Metadata-Version: 2.2
Name: graphrag_tagger
Version: 0.1.1
Summary: A lightweight toolkit for extracting topics from PDFs and visualizing their connections using graphs.
Home-page: https://github.com/KameniAlexNea/graphrag-tagger
Author: Alex Kameni
Author-email: kamenialexnea@gmail.com
Classifier: Programming Language :: Python :: 3
Classifier: Operating System :: OS Independent
Requires-Python: >=3.6
License-File: LICENSE
Requires-Dist: aisuite[ollama]
Requires-Dist: scikit-learn
Requires-Dist: ktrain
Requires-Dist: docstring_parser
Requires-Dist: ollama
Requires-Dist: langchain-text-splitters
Requires-Dist: PyMuPDF
Requires-Dist: tiktoken
Requires-Dist: networkx
Requires-Dist: tqdm
Dynamic: author
Dynamic: author-email
Dynamic: classifier
Dynamic: description
Dynamic: description-content-type
Dynamic: home-page
Dynamic: requires-dist
Dynamic: requires-python
Dynamic: summary
